README.rst
setup.py
json_variable/__init__.py
json_variable/dereferencing.py
json_variable.egg-info/PKG-INFO
json_variable.egg-info/SOURCES.txt
json_variable.egg-info/dependency_links.txt
json_variable.egg-info/requires.txt
json_variable.egg-info/top_level.txt