Metadata-Version: 1.1
Name: json-variable
Version: 0.0.1
Summary: Sub-string Extension to JSON Pointer References.
Home-page: https://github.com/theengineear/json_variable
Author: Andrew Seier
Author-email: andseier@gmail.com
License: MIT
Platform: UNKNOWN
Classifier: Development Status :: 4 - Beta
Classifier: Programming Language :: Python :: 2
Classifier: Programming Language :: Python :: 3
